<?xml version="1.0" encoding="UTF-8"?>
<document xmlns:xsi="http://www.w3.org/2001/XMLSchema-instance" xsi:noNamespaceSchemaLocation="http://www.uni-weimar.de/medien/webis/research/corpora/pan-pc-09/document.xsd" reference="suspicious-document00760.txt">
  <feature name="project-gutenberg" etext_number="19766" url="http://www.gutenberg.org/files/19766/19766-8.txt"/>
  <feature name="language" value="en" />
  <feature name="artificial-plagiarism" translation="false" obfuscation="high" this_offset="4909" this_length="4900" source_reference="source-document05996.txt" source_offset="135043" source_length="5056" />
  <feature name="artificial-plagiarism" translation="false" obfuscation="none" this_offset="32785" this_length="17032" source_reference="source-document06843.txt" source_offset="163382" source_length="17000" />
  <feature name="artificial-plagiarism" translation="false" obfuscation="none" this_offset="100261" this_length="24543" source_reference="source-document05996.txt" source_offset="194024" source_length="24508" />
  <feature name="artificial-plagiarism" translation="false" obfuscation="low" this_offset="181941" this_length="19007" source_reference="source-document05996.txt" source_offset="162908" source_length="19379" />
  <feature name="artificial-plagiarism" translation="false" obfuscation="none" this_offset="226995" this_length="4599" source_reference="source-document05996.txt" source_offset="4091" source_length="4835" />
  <feature name="artificial-plagiarism" translation="false" obfuscation="low" this_offset="235714" this_length="1457" source_reference="source-document05996.txt" source_offset="46554" source_length="1522" />
  <feature name="artificial-plagiarism" translation="false" obfuscation="low" this_offset="242119" this_length="3149" source_reference="source-document06843.txt" source_offset="117454" source_length="3259" />
  <feature name="artificial-plagiarism" translation="false" obfuscation="none" this_offset="256719" this_length="4531" source_reference="source-document06843.txt" source_offset="24924" source_length="4518" />
  <feature name="artificial-plagiarism" translation="false" obfuscation="high" this_offset="266800" this_length="709" source_reference="source-document05996.txt" source_offset="110625" source_length="709" />
  <feature name="artificial-plagiarism" translation="false" obfuscation="high" this_offset="272212" this_length="1694" source_reference="source-document05996.txt" source_offset="94597" source_length="1761" />
  <feature name="artificial-plagiarism" translation="false" obfuscation="low" this_offset="275472" this_length="784" source_reference="source-document05361.txt" source_offset="650" source_length="772" />
  <!-- Use tags like the one below to annotate plagiarism you detected. -->
  <!-- <feature name="detected-plagiarism" this_offset="50" this_length="1000" source_reference="source-documentX.txt" source_offset="750" source_length="1700"/> -->
</document>

