<?xml version="1.0" encoding="UTF-8"?>
<document xmlns:xsi="http://www.w3.org/2001/XMLSchema-instance" xsi:noNamespaceSchemaLocation="http://www.uni-weimar.de/medien/webis/research/corpora/pan-pc-09/document.xsd" reference="suspicious-document00288.txt">
  <feature name="project-gutenberg" etext_number="3292" url="http://www.gutenberg.org/files/3292/3292-8.txt"/>
  <feature name="language" value="en" />
  <feature name="artificial-plagiarism" translation="false" obfuscation="low" this_offset="228" this_length="4605" source_reference="source-document03151.txt" source_offset="185172" source_length="4503" />
  <feature name="artificial-plagiarism" translation="false" obfuscation="none" this_offset="4915" this_length="695" source_reference="source-document02585.txt" source_offset="0" source_length="696" />
  <feature name="artificial-plagiarism" translation="false" obfuscation="low" this_offset="5833" this_length="768" source_reference="source-document03151.txt" source_offset="195335" source_length="773" />
  <feature name="artificial-plagiarism" translation="false" obfuscation="low" this_offset="6963" this_length="718" source_reference="source-document03151.txt" source_offset="181695" source_length="705" />
  <feature name="artificial-plagiarism" translation="false" obfuscation="high" this_offset="7681" this_length="233" source_reference="source-document03151.txt" source_offset="174018" source_length="238" />
  <!-- Use tags like the one below to annotate plagiarism you detected. -->
  <!-- <feature name="detected-plagiarism" this_offset="50" this_length="1000" source_reference="source-documentX.txt" source_offset="750" source_length="1700"/> -->
</document>

